.bzrignore
CHANGES.txt
CONTRIBUTORS.txt
README.txt
setup.py
django_cachepurge/__init__.py
django_cachepurge/config.py
django_cachepurge/middleware.py
django_cachepurge/models.py
django_cachepurge/settings_tests.py
django_cachepurge/utils.py
django_cachepurge.egg-info/PKG-INFO
django_cachepurge.egg-info/SOURCES.txt
django_cachepurge.egg-info/dependency_links.txt
django_cachepurge.egg-info/entry_points.txt
django_cachepurge.egg-info/not-zip-safe
django_cachepurge.egg-info/top_level.txt
django_cachepurge/tests/__init__.py
django_cachepurge/tests/testingmodels.py
django_cachepurge/tests/urls.py