Metadata-Version: 1.0
Name: django-cachepurge
Version: 0.3
Summary: Django Middleware and utilities that send "PURGE" request to an upstream cache
Home-page: http://launchpad.net/django-cachepurge
Author: Bertrand Mathieu
Author-email: bert.mathieu@gmail.com
License: GPL
Keywords: django cache squid varnish
Platform: UNKNOWN
Classifier: Development Status :: 5 - Production/Stable
Classifier: Environment :: Web Environment
Classifier: Framework :: Django
Classifier: Intended Audience :: Developers
Classifier: Topic :: Internet :: Proxy Servers
Classifier: License :: OSI Approved :: GNU General Public License (GPL)
